citibox/google_cloud_tracer/__init__.py
citibox/google_cloud_tracer/contrib/__init__.py
citibox/google_cloud_tracer/contrib/django/__init__.py
citibox/google_cloud_tracer/contrib/django/django_middleware.py
citibox/google_cloud_tracer/contrib/falcon/__init__.py
citibox/google_cloud_tracer/contrib/falcon/falcon_middleware.py
citibox/google_cloud_tracer/gcp_integration/__init__.py
citibox/google_cloud_tracer/gcp_integration/pubsub_publisher/__init__.py
citibox/google_cloud_tracer/requests/__init__.py
citibox/google_cloud_tracer/span_context/__init__.py
citibox/google_cloud_tracer/tracer/__init__.py
citibox_tracer-0.2.10.dist-info/METADATA
citibox_tracer-0.2.10.dist-info/WHEEL
citibox_tracer-0.2.10.dist-info/top_level.txt
citibox_tracer-0.2.10.dist-info/RECORD
