Metadata-Version: 2.1
Name: citibox-tracer
Version: 0.2.10
Summary: Citibox Google tracing tools
Home-page: https://citibox.com
Author: Citibox
License: UNKNOWN
Platform: UNKNOWN
Classifier: Programming Language :: Python :: 3
Classifier: License :: OSI Approved :: MIT License
Classifier: Operating System :: OS Independent
Requires-Python: >=3.6
Requires-Dist: opencensus (==0.7.13)
Requires-Dist: opencensus-ext-django (==0.7.5)
Requires-Dist: opencensus-ext-stackdriver (<0.8,>=0.7)
Requires-Dist: google-cloud-pubsub (<1.7,>=1.6)
